ai_proxy_core/__init__.py
ai_proxy_core/completion_client.py
ai_proxy_core/gemini_live.py
ai_proxy_core/models.py
ai_proxy_core/telemetry.py
ai_proxy_core/providers/__init__.py
ai_proxy_core/providers/base.py
ai_proxy_core/providers/google.py
ai_proxy_core/providers/model_providers.py
ai_proxy_core/providers/ollama.py
ai_proxy_core/providers/openai.py
ai_proxy_core/providers/openai_image.py
ai_proxy_core-0.4.42.dist-info/licenses/LICENSE
ai_proxy_core-0.4.42.dist-info/METADATA
ai_proxy_core-0.4.42.dist-info/WHEEL
ai_proxy_core-0.4.42.dist-info/top_level.txt
ai_proxy_core-0.4.42.dist-info/RECORD
