Metadata-Version: 2.4
Name: ai-proxy-core
Version: 0.4.42
Summary: Minimal, reusable AI service handlers for Gemini and other LLMs
Home-page: https://github.com/ebowwa/ai-proxy-core
Author: ebowwa
Author-email: ebowwa <your-email@example.com>
License: MIT
Project-URL: Homepage, https://github.com/ebowwa/ai-proxy-core
Project-URL: Repository, https://github.com/ebowwa/ai-proxy-core
Project-URL: Issues, https://github.com/ebowwa/ai-proxy-core/issues
Keywords: ai,gemini,llm,api,proxy
Classifier: Programming Language :: Python :: 3
Classifier: License :: OSI Approved :: MIT License
Classifier: Operating System :: OS Independent
Classifier: Development Status :: 4 - Beta
Classifier: Intended Audience :: Developers
Classifier: Topic :: Software Development :: Libraries :: Python Modules
Requires-Python: >=3.9
License-File: LICENSE
Requires-Dist: google-genai>=0.1.0
Requires-Dist: pillow>=10.0.0
Requires-Dist: aiohttp>=3.8.0
Requires-Dist: openai>=1.99.5
Provides-Extra: dev
Requires-Dist: pytest>=7.0.0; extra == "dev"
Requires-Dist: pytest-asyncio>=0.21.0; extra == "dev"
Requires-Dist: build>=0.10.0; extra == "dev"
Requires-Dist: twine>=4.0.0; extra == "dev"
Provides-Extra: telemetry
Requires-Dist: opentelemetry-api>=1.20.0; extra == "telemetry"
Requires-Dist: opentelemetry-sdk>=1.20.0; extra == "telemetry"
Requires-Dist: opentelemetry-exporter-otlp>=1.20.0; extra == "telemetry"
Provides-Extra: openai
Requires-Dist: openai>=1.0.0; extra == "openai"
Provides-Extra: anthropic
Requires-Dist: anthropic>=0.18.0; extra == "anthropic"
Provides-Extra: all
Requires-Dist: openai>=1.0.0; extra == "all"
Requires-Dist: anthropic>=0.18.0; extra == "all"
Requires-Dist: opentelemetry-api>=1.20.0; extra == "all"
Requires-Dist: opentelemetry-sdk>=1.20.0; extra == "all"
Requires-Dist: opentelemetry-exporter-otlp>=1.20.0; extra == "all"
Dynamic: author
Dynamic: home-page
Dynamic: license-file
Dynamic: requires-python
